generate_scroller/__init__.py
generate_scroller/cli.py
generate_scroller-1.0.1.dist-info/licenses/LICENSE
generate_scroller-1.0.1.dist-info/METADATA
generate_scroller-1.0.1.dist-info/WHEEL
generate_scroller-1.0.1.dist-info/entry_points.txt
generate_scroller-1.0.1.dist-info/top_level.txt
generate_scroller-1.0.1.dist-info/RECORD
