Metadata-Version: 2.4
Name: generate_scroller
Version: 1.0.1
Summary: Un outil CLI pour générer un fichier scroller.md avec tous les fichiers texte d'un répertoire.
Author: Daniel Guedegbe
Author-email: Ton Nom <danielguedebe10027@gmail.com>
License: MIT
Keywords: cli,markdown,files,scanner,dev-tools
Classifier: Programming Language :: Python :: 3
Classifier: License :: OSI Approved :: MIT License
Classifier: Operating System :: OS Independent
Requires-Python: >=3.6
License-File: LICENSE
Dynamic: author
Dynamic: license-file
Dynamic: requires-python
